md5: 548b1fae17f85d8ea7525de047939ddc

version: Java 16 (60)
access: ACC_PUBLIC (33)

source: bridgeTest.cai

!signature: Ljava/lang/Object;Lcom/AB<Ljava/util/List;>;
!extends: java/lang/Object
!implements: [com/AB]
public class com.bridgeTest extends java.lang.Object implements com.AB {

    !access: ACC_PUBLIC, ACC_BRIDGE (65)
    !signature: (TT;)V
    !parameter[name: iter, access:  (0)]
    public void iterate(java.lang.Object) {
      desc: (Ljava/lang/Object;)V 
      maxStack: 2, maxLocals: 2 
      Label_0:
        aload 0
        aload 1
        checkcast java.util.List
        invokevirtual com.bridgeTest.iterate(java.util.List)void (ownerIsInterface: false)
        return
      Label_1:
      LocalVariables {
        index: 1, name: iter, start: Label_0, end: Label_1, type: java.lang.Object, signature: TT;
        index: 0, name: this, start: Label_0, end: Label_1, type: com.bridgeTest, signature: null
      }
    }
    
    !access: ACC_PUBLIC, ACC_BRIDGE (65)
    !signature: (Ljava/lang/Iterable;)V
    !parameter[name: iter, access:  (0)]
    public void iterate(java.lang.Iterable) {
      desc: (Ljava/lang/Iterable;)V 
      maxStack: 2, maxLocals: 2 
      Label_0:
        aload 0
        aload 1
        checkcast java.util.List
        invokevirtual com.bridgeTest.iterate(java.util.List)void (ownerIsInterface: false)
        return
      Label_1:
      LocalVariables {
        index: 1, name: iter, start: Label_0, end: Label_1, type: java.lang.Iterable, signature: Ljava/lang/Iterable<*>;
        index: 0, name: this, start: Label_0, end: Label_1, type: com.bridgeTest, signature: null
      }
    }
    
    !access: ACC_PUBLIC (1)
    !parameter[name: iter, access:  (0)]
    public void iterate(java.util.List) {
      desc: (Ljava/util/List;)V 
      maxStack: 2, maxLocals: 4 
      Label_0:
        aload 1
        iconst_0
        invokeinterface java.util.List.get(int)java.lang.Object (ownerIsInterface: true)
        pop
        aload 1
        invokeinterface java.lang.Iterable.iterator()java.util.Iterator (ownerIsInterface: true)
        astore 2
      Label_1:
       FRAME[type: F_APPEND, locals: 1, local: {Reference[java.util.Iterator]}, stacks: 0, stack: {}]
        aload 2
        invokeinterface java.util.Iterator.hasNext()boolean (ownerIsInterface: true)
        ifeq Label_3
        aload 2
        invokeinterface java.util.Iterator.next()java.lang.Object (ownerIsInterface: true)
      Label_2:
        astore 3
        getstatic java.lang.System.out (type: java.io.PrintStream)
        aload 3
        invokevirtual java.lang.Object.toString()java.lang.String (ownerIsInterface: false)
        invokevirtual java.io.PrintStream.println(java.lang.Object)void (ownerIsInterface: false)
        goto Label_1
      Label_3:
       FRAME[type: F_SAME, locals: 0, local: {}, stacks: 0, stack: {}]
        return
      Label_4:
      LocalVariables {
        index: 3, name: obj, start: Label_2, end: Label_3, type: java.lang.Object, signature: null
        index: 1, name: iter, start: Label_0, end: Label_4, type: java.util.List, signature: null
        index: 0, name: this, start: Label_0, end: Label_4, type: com.bridgeTest, signature: null
      }
    }
    
    !access: ACC_PUBLIC (1)
    public void <init>() {
      desc: ()V 
      maxStack: 1, maxLocals: 1 
      Label_0:
        aload 0
        invokespecial java.lang.Object.<init>()void (ownerIsInterface: false)
        return
      Label_1:
      LocalVariables {
        index: 0, name: this, start: Label_0, end: Label_1, type: com.bridgeTest, signature: null
      }
    }
    
    !access: PACKAGE_PRIVATE, ACC_STATIC (8)
    static void <clinit>() {
      desc: ()V 
      maxStack: 0, maxLocals: 0 
        return
    }
    
}