md5: b3814503f16ca9ec598c1af6727a7649

version: Java 8 (52)
access: ACC_PUBLIC (33)

source: ComplexIf3.cai

public class test.ComplexIf3 extends java.lang.Object {

    !access: ACC_PUBLIC (1)
    !parameter[name: h, access:  (0)]
    !parameter[name: x, access:  (0)]
    !parameter[name: y, access:  (0)]
    !parameter[name: z, access:  (0)]
    !parameter[name: p, access:  (0)]
    !parameter[name: v, access:  (0)]
    public void <init>(boolean, boolean, boolean, boolean, boolean, boolean) {
      desc: (ZZZZZZ)V 
      maxStack: 2, maxLocals: 7 
      Label_0:
        aload 0
        invokespecial java.lang.Object.<init>()void (ownerIsInterface: false)
      Label_1:
       LINE 1 -> Label_1
        iload 1
        ifeq Label_2
        iload 2
        ifeq Label_2
        iload 3
        ifne Label_3
        iload 4
        ifne Label_3
      Label_2:
       FRAME[type: F_FULL, locals: 7, local: {Reference[test.ComplexIf3], Primitive[integer], Primitive[integer], Primitive[integer], Primitive[integer], Primitive[integer], Primitive[integer]}, stacks: 0, stack: {}]
        iload 5
        ifne Label_3
        iload 6
        ifeq Label_4
      Label_3:
       LINE 2 -> Label_3
       FRAME[type: F_SAME, locals: 0, local: {}, stacks: 0, stack: {}]
        getstatic java.lang.System.out (type: java.io.PrintStream)
        ldc "true"              // type: java.lang.String
        invokevirtual java.io.PrintStream.println(java.lang.String)void (ownerIsInterface: false)
        goto Label_5
      Label_4:
       LINE 3 -> Label_4
       FRAME[type: F_SAME, locals: 0, local: {}, stacks: 0, stack: {}]
        getstatic java.lang.System.out (type: java.io.PrintStream)
        ldc "false"              // type: java.lang.String
        invokevirtual java.io.PrintStream.println(java.lang.String)void (ownerIsInterface: false)
      Label_5:
       FRAME[type: F_SAME, locals: 0, local: {}, stacks: 0, stack: {}]
        return
      Label_6:
      LocalVariables {
        index: 6, name: v, start: Label_0, end: Label_6, type: boolean, signature: null
        index: 5, name: p, start: Label_0, end: Label_6, type: boolean, signature: null
        index: 4, name: z, start: Label_0, end: Label_6, type: boolean, signature: null
        index: 3, name: y, start: Label_0, end: Label_6, type: boolean, signature: null
        index: 2, name: x, start: Label_0, end: Label_6, type: boolean, signature: null
        index: 1, name: h, start: Label_0, end: Label_6, type: boolean, signature: null
        index: 0, name: this, start: Label_0, end: Label_6, type: test.ComplexIf3, signature: null
      }
    }
    
    !access: PACKAGE_PRIVATE, ACC_STATIC (8)
    static void <clinit>() {
      desc: ()V 
      maxStack: 0, maxLocals: 0 
        return
    }
    
}