md5: 2133a08bb1dbdcce33a4beb30ab13c53

version: Java 8 (52)
access: ACC_PUBLIC (33)

source: ConcatTest.cai

public class com.ConcatTest extends java.lang.Object {

    !access: ACC_PUBLIC (1)
    !parameter[name: av, access:  (0)]
    public void <init>(java.lang.String) {
      desc: (Ljava/lang/String;)V 
      maxStack: 4, maxLocals: 2 
      Label_0:
        aload 0
        invokespecial java.lang.Object.<init>()void (ownerIsInterface: false)
      Label_1:
       LINE 3 -> Label_1
        getstatic java.lang.System.out (type: java.io.PrintStream)
        new java.lang.StringBuilder
        dup
        ldc "Hello"              // type: java.lang.String
        invokespecial java.lang.StringBuilder.<init>(java.lang.String)void (ownerIsInterface: false)
        ldc " "              // type: java.lang.String
        invokevirtual java.lang.StringBuilder.append(java.lang.String)java.lang.StringBuilder (ownerIsInterface: false)
        aload 1
        invokevirtual java.lang.StringBuilder.append(java.lang.String)java.lang.StringBuilder (ownerIsInterface: false)
        ldc " :D"              // type: java.lang.String
        invokevirtual java.lang.StringBuilder.append(java.lang.String)java.lang.StringBuilder (ownerIsInterface: false)
        invokevirtual java.lang.Object.toString()java.lang.String (ownerIsInterface: false)
        invokevirtual java.io.PrintStream.println(java.lang.String)void (ownerIsInterface: false)
      Label_2:
       LINE 4 -> Label_2
        getstatic java.lang.System.out (type: java.io.PrintStream)
        ldc ""              // type: java.lang.String
        invokevirtual java.io.PrintStream.println(java.lang.String)void (ownerIsInterface: false)
      Label_3:
       LINE 5 -> Label_3
        getstatic java.lang.System.out (type: java.io.PrintStream)
        ldc "A"              // type: java.lang.String
        invokevirtual java.io.PrintStream.println(java.lang.String)void (ownerIsInterface: false)
      Label_4:
       LINE 6 -> Label_4
        getstatic java.lang.System.out (type: java.io.PrintStream)
        ldc "A"              // type: java.lang.String
        ldc "B"              // type: java.lang.String
        invokevirtual java.lang.String.concat(java.lang.String)java.lang.String (ownerIsInterface: false)
        invokevirtual java.io.PrintStream.println(java.lang.String)void (ownerIsInterface: false)
        return
      Label_5:
      LocalVariables {
        index: 1, name: av, start: Label_0, end: Label_5, type: java.lang.String, signature: null
        index: 0, name: this, start: Label_0, end: Label_5, type: com.ConcatTest, signature: null
      }
    }
    
    !access: PACKAGE_PRIVATE, ACC_STATIC (8)
    static void <clinit>() {
      desc: ()V 
      maxStack: 0, maxLocals: 0 
        return
    }
    
}