md5: db6ce0b3e5921c4b71ef401579047749

version: Java 16 (60)
access: ACC_PUBLIC (16417)

source: Option.cai

!signature: <T:Ljava/lang/Object;>Ljava/lang/Enum<Lcom/Option;>;
!extends: java/lang/Enum
!implements: []
!NestMember: com/Option$Some
!NestMember: com/Option$None
public enum com.Option extends java.lang.Enum {

    inner {
        !access: ACC_PUBLIC (9)
        public com.Option.Some -> com.Option$Some
        !access: ACC_PUBLIC (9)
        public com.Option.None -> com.Option$None
    }

    !access: ACC_PUBLIC, ACC_STATIC, ACC_FINAL (16409)
    public static final com.Option$None None
    !access: ACC_PUBLIC, ACC_STATIC, ACC_FINAL (16409)
    !signature: Lcom/Option$Some<Lcom/Option$None;>;
    public static final com.Option$Some Some
    !access: ACC_PRIVATE, ACC_STATIC, ACC_FINAL, ACC_SYNTHETIC (4122)
    private static final com.Option[] $VALUES

    !access: PACKAGE_PRIVATE (0)
    !parameter[name: name, access:  (0)]
    !parameter[name: ordinal, access:  (0)]
     void <init>(java.lang.String, int) {
      desc: (Ljava/lang/String;I)V 
      maxStack: 3, maxLocals: 3 
      Label_0:
       LINE 14 -> Label_0
        aload 0
        aload 1
        iload 2
        invokespecial java.lang.Enum.<init>(java.lang.String, int)void (ownerIsInterface: false)
        return
      Label_1:
      LocalVariables {
        index: 2, name: ordinal, start: Label_0, end: Label_1, type: int, signature: null
        index: 1, name: name, start: Label_0, end: Label_1, type: java.lang.String, signature: null
        index: 0, name: this, start: Label_0, end: Label_1, type: com.Option, signature: null
      }
    }
    
    !access: ACC_PUBLIC, ACC_STATIC (9)
    !signature: <T:Ljava/lang/Object;>(TT;)Lcom/Option$Some<TT;>;
    !parameter[name: value, access:  (0)]
    public static com.Option$Some some(java.lang.Object) {
      desc: (Ljava/lang/Object;)Lcom/Option$Some; 
      maxStack: 3, maxLocals: 1 
      Label_0:
       LINE 1 -> Label_0
        new com.Option$Some
        dup
        aload 0
        invokespecial com.Option$Some.<init>(java.lang.Object)void (ownerIsInterface: false)
        areturn
      Label_1:
      LocalVariables {
        index: 0, name: value, start: Label_0, end: Label_1, type: java.lang.Object, signature: TT;
      }
    }
    
    !access: ACC_PUBLIC, ACC_STATIC (9)
    public static com.Option$None none() {
      desc: ()Lcom/Option$None; 
      maxStack: 1, maxLocals: 0 
      Label_0:
       LINE 2 -> Label_0
        getstatic com.Option.None (type: com.Option$None)
        areturn
    }
    
    !access: ACC_PUBLIC, ACC_STATIC (9)
    public static com.Option[] values() {
      desc: ()[Lcom/Option; 
      maxStack: 1, maxLocals: 0 
      Label_0:
       LINE 3 -> Label_0
        getstatic com.Option.$VALUES (type: com.Option[])
        invokevirtual com.Option[].clone()java.lang.Object (ownerIsInterface: false)
        checkcast com.Option[]
        areturn
    }
    
    !access: ACC_PUBLIC, ACC_STATIC (9)
    !parameter[name: name, access:  (0)]
    public static com.Option valueOf(java.lang.String) {
      desc: (Ljava/lang/String;)Lcom/Option; 
      maxStack: 2, maxLocals: 1 
      Label_0:
       LINE 4 -> Label_0
        ldc Lcom/Option;              // type: java.lang.Class
        aload 0
        invokestatic java.lang.Enum.valueOf(java.lang.Class, java.lang.String)java.lang.Enum (ownerIsInterface: false)
        checkcast com.Option
        areturn
      Label_1:
      LocalVariables {
        index: 0, name: name, start: Label_0, end: Label_1, type: java.lang.String, signature: null
      }
    }
    
    !access: PACKAGE_PRIVATE, ACC_STATIC (8)
    static void <clinit>() {
      desc: ()V 
      maxStack: 4, maxLocals: 0 
      Label_0:
       LINE 11 -> Label_0
        new com.Option$None
        dup
        invokespecial com.Option$None.<init>()void (ownerIsInterface: false)
        putstatic com.Option.None (type: com.Option$None)
      Label_1:
       LINE 12 -> Label_1
        new com.Option$Some
        dup
        getstatic com.Option.None (type: com.Option$None)
        invokespecial com.Option$Some.<init>(java.lang.Object)void (ownerIsInterface: false)
        putstatic com.Option.Some (type: com.Option$Some)
      Label_2:
       LINE 13 -> Label_2
        iconst_2
        anewarray com.Option
        dup
        iconst_0
        getstatic com.Option.Some (type: com.Option$Some)
        checkcast com.Option
        aastore
        dup
        iconst_1
        getstatic com.Option.None (type: com.Option$None)
        checkcast com.Option
        aastore
        putstatic com.Option.$VALUES (type: com.Option[])
        return
    }
    
}