md5: 60152287c35cabcd302e8246bcee5ab3

version: Java 8 (52)
access: ACC_PUBLIC (33)

source: InnerClass.cai

public class test.InnerClass extends java.lang.Object {

    !access: ACC_PUBLIC (1)
    public test.InnerClass.Inner -> test.InnerClass$Inner

    !access: ACC_PRIVATE (2)
    private java.lang.String field

    !access: ACC_PUBLIC (1)
    public void <init>() {
      desc: ()V 
      maxStack: 3, maxLocals: 1 
      Label_0:
        aload 0
        invokespecial java.lang.Object.<init>()void (ownerIsInterface: false)
        aload 0
        ldc "XSD"              // type: java.lang.String
        putfield test.InnerClass.field (type: java.lang.String)
      Label_1:
       LINE 6 -> Label_1
        new test.InnerClass$Inner
        dup
        aload 0
        invokespecial test.InnerClass$Inner.<init>(test.InnerClass)void (ownerIsInterface: false)
        invokevirtual test.InnerClass$Inner.invoke$000()java.lang.String (ownerIsInterface: false)
        return
      Label_2:
      LocalVariables {
        index: 0, name: this, start: Label_0, end: Label_2, type: test.InnerClass, signature: null
      }
    }
    
    !access: ACC_PRIVATE (2)
    private void <init>(java.lang.String) {
      desc: (Ljava/lang/String;)V 
      maxStack: 2, maxLocals: 2 
      Label_0:
        aload 0
        invokespecial java.lang.Object.<init>()void (ownerIsInterface: false)
        aload 0
        ldc "XSD"              // type: java.lang.String
        putfield test.InnerClass.field (type: java.lang.String)
      Label_1:
       LINE 7 -> Label_1
        getstatic java.lang.System.out (type: java.io.PrintStream)
        aload 1
        invokevirtual java.io.PrintStream.println(java.lang.Object)void (ownerIsInterface: false)
        return
      Label_2:
      LocalVariables {
        index: 1, name: str, start: Label_0, end: Label_2, type: java.lang.String, signature: null
        index: 0, name: this, start: Label_0, end: Label_2, type: test.InnerClass, signature: null
      }
    }
    
    !access: ACC_PUBLIC (1)
    public void mm() {
      desc: ()V 
      maxStack: 2, maxLocals: 1 
      Label_0:
       LINE 8 -> Label_0
        getstatic java.lang.System.out (type: java.io.PrintStream)
        ldc "A"              // type: java.lang.String
        invokevirtual java.io.PrintStream.println(java.lang.Object)void (ownerIsInterface: false)
        return
      Label_1:
      LocalVariables {
        index: 0, name: this, start: Label_0, end: Label_1, type: test.InnerClass, signature: null
      }
    }
    
    !access: PACKAGE_PRIVATE, ACC_STATIC (8)
    static void <clinit>() {
      desc: ()V 
      maxStack: 0, maxLocals: 0 
        return
    }
    
    !access: PACKAGE_PRIVATE, ACC_SYNTHETIC (4096)
     java.lang.String invoke$000() {
      desc: ()Ljava/lang/String; 
      maxStack: 1, maxLocals: 1 
      Label_0:
       LINE 9 -> Label_0
        aload 0
        getfield test.InnerClass.field (type: java.lang.String)
        areturn
      Label_1:
      LocalVariables {
        index: 0, name: this, start: Label_0, end: Label_1, type: test.InnerClass, signature: null
      }
    }
    
    !access: PACKAGE_PRIVATE, ACC_SYNTHETIC (4096)
     void <init>(java.lang.String, test.InnerClass$Inner) {
      desc: (Ljava/lang/String;Ltest/InnerClass$Inner;)V 
      maxStack: 2, maxLocals: 3 
      Label_0:
       LINE 10 -> Label_0
        aload 0
        aload 1
        invokespecial test.InnerClass.<init>(java.lang.String)void (ownerIsInterface: false)
        return
      Label_1:
      LocalVariables {
        index: 2, name: $inner, start: Label_0, end: Label_1, type: test.InnerClass$Inner, signature: null
        index: 1, name: str, start: Label_0, end: Label_1, type: java.lang.String, signature: null
        index: 0, name: this, start: Label_0, end: Label_1, type: test.InnerClass, signature: null
      }
    }
    
}