md5: b21fffb96b8f02c82ed2a7f71c116574

version: Java 8
access: ACC_PUBLIC

source: OperateTest.cai

public class com.OperateTest extends java.lang.Object {

    !access: ACC_PUBLIC
    public void <init>(int) {
      desc: (I)V 
      maxStack: 4, maxLocals: 2 
      Label_0:
        aload 0
        invokespecial java.lang.Object.<init>()void (ownerIsInterface: false)
      Label_1:
       LINE 3 -> Label_1
        getstatic java.lang.System.out (type: java.io.PrintStream)
        bipush org.objectweb.asm.tree.IntInsnNode@34e9fd99.operand
        iload 1
        iadd
        iload 1
        iconst_2
        imul
        iadd
        invokestatic java.lang.String.valueOf(int)java.lang.String (ownerIsInterface: false)
        invokevirtual java.io.PrintStream.println(java.lang.String)void (ownerIsInterface: false)
      Label_2:
       LINE 4 -> Label_2
        getstatic java.lang.System.out (type: java.io.PrintStream)
        bipush org.objectweb.asm.tree.IntInsnNode@3c41ed1d.operand
        ineg
        invokestatic java.lang.String.valueOf(int)java.lang.String (ownerIsInterface: false)
        invokevirtual java.io.PrintStream.println(java.lang.String)void (ownerIsInterface: false)
      Label_3:
       LINE 5 -> Label_3
        getstatic java.lang.System.out (type: java.io.PrintStream)
        bipush org.objectweb.asm.tree.IntInsnNode@54d9d12d.operand
        bipush org.objectweb.asm.tree.IntInsnNode@38425407.operand
        iconst_m1
        ixor
        isub
        invokestatic java.lang.String.valueOf(int)java.lang.String (ownerIsInterface: false)
        invokevirtual java.io.PrintStream.println(java.lang.String)void (ownerIsInterface: false)
        return
      Label_4:
      LocalVariables {
        index: 0, start: Label_0, end: Label_0, type: com.OperateTest, signature: null
        index: 1, start: Label_0, end: Label_0, type: int, signature: null
      }
    }
    
    !access: PACKAGE_PRIVATE, ACC_STATIC
    static void <clinit>() {
      desc: ()V 
      maxStack: 0, maxLocals: 0 
        return
    }
    
}