md5: 08f81a8baf1d465f2ad21050bbfa96f1

version: Java 8 (52)
access: ACC_PUBLIC (33)

source: SimpleTest2_bytecode.cai

public class me.jonathanscripter.codeapi.test.SimpleTest2_bytecode extends java.lang.Object {

    !access: ACC_PUBLIC, ACC_FINAL (17)
    public final java.lang.String myField

    !access: ACC_PUBLIC (1)
    !parameter[name: myField, access:  (0)]
    public void <init>(java.lang.String) {
      desc: (Ljava/lang/String;)V 
      maxStack: 4, maxLocals: 2 
      Label_0:
        aload 0
        invokespecial java.lang.Object.<init>()void (ownerIsInterface: false)
        aload 0
        aload 1
        putfield me.jonathanscripter.codeapi.test.SimpleTest2_bytecode.myField (type: java.lang.String)
        aload 1
        ifnull Label_1
        getstatic java.lang.System.out (type: java.io.PrintStream)
        aload 1
        invokevirtual java.io.PrintStream.println(java.lang.String)void (ownerIsInterface: false)
        goto Label_2
      Label_1:
       FRAME[type: F_FULL, locals: 2, local: {Reference[me.jonathanscripter.codeapi.test.SimpleTest2_bytecode], Reference[java.lang.String]}, stacks: 0, stack: {}]
        getstatic java.lang.System.out (type: java.io.PrintStream)
        ldc "NULL VALUE"              // type: java.lang.String
        invokevirtual java.io.PrintStream.println(java.lang.String)void (ownerIsInterface: false)
      Label_2:
       FRAME[type: F_SAME, locals: 0, local: {}, stacks: 0, stack: {}]
        ldc 5894567987              // type: java.lang.Long
        ldc 89859845678798              // type: java.lang.Long
        lcmp
        ifge Label_3
        getstatic java.lang.System.out (type: java.io.PrintStream)
        ldc "First < Second"              // type: java.lang.String
        invokevirtual java.io.PrintStream.println(java.lang.String)void (ownerIsInterface: false)
        goto Label_4
      Label_3:
       FRAME[type: F_SAME, locals: 0, local: {}, stacks: 0, stack: {}]
        getstatic java.lang.System.out (type: java.io.PrintStream)
        ldc "First >= Second"              // type: java.lang.String
        invokevirtual java.io.PrintStream.println(java.lang.String)void (ownerIsInterface: false)
      Label_4:
       FRAME[type: F_SAME, locals: 0, local: {}, stacks: 0, stack: {}]
        return
      Label_5:
      LocalVariables {
        index: 1, name: myField, start: Label_0, end: Label_5, type: java.lang.String, signature: null
        index: 0, name: this, start: Label_0, end: Label_5, type: me.jonathanscripter.codeapi.test.SimpleTest2_bytecode, signature: null
      }
    }
    
    !access: PACKAGE_PRIVATE, ACC_STATIC (8)
    static void <clinit>() {
      desc: ()V 
      maxStack: 0, maxLocals: 0 
        return
    }
    
}