md5: 95bee8bb33e3b51ea7151d259c4cea36

version: 52 (Java 8)
access: 33 (ACC_PUBLIC)

source: SwitchTestClass.cai, debug: null
public class com.SwitchTestClass extends java.lang.Object {

    !access: 1 (ACC_PUBLIC)
    public void <init>(int, int, com.github.jonathanxd.codeapi.test.SwitchTest_$TestEnum, java.lang.String, java.lang.Object) {
      Label_0:
        aload 0
        invokespecial java.lang.Object.<init>()void (ownerIsInterface: false)
      Label_1:
       LINE 3 -> Label_1
        iload 1
        tableSwitch(1..5) {
            handler 0: Label_2
            handler 1: Label_3
            handler 2: Label_4
            handler 3: Label_3
            handler 4: Label_5
            default: Label_3
        }
      Label_2:
       LINE 8 -> Label_2
       FRAME[type: F_FULL, locals: 6, local: {com.SwitchTestClass, integer, integer, com.github.jonathanxd.codeapi.test.SwitchTest_$TestEnum, java.lang.String, java.lang.Object}, stacks: 0, stack: {}]
        getstatic java.lang.System.out (type: java.io.PrintStream)
        ldc "1"
        invokevirtual java.io.PrintStream.println(java.lang.Object)void (ownerIsInterface: false)
      Label_6:
       LINE 9 -> Label_6
        goto Label_7
      Label_4:
       LINE 10 -> Label_4
       FRAME[type: F_SAME, locals: 0, local: {com.SwitchTestClass, integer, integer, com.github.jonathanxd.codeapi.test.SwitchTest_$TestEnum, java.lang.String, java.lang.Object}, stacks: 0, stack: {}]
        getstatic java.lang.System.out (type: java.io.PrintStream)
        ldc "3"
        invokevirtual java.io.PrintStream.println(java.lang.Object)void (ownerIsInterface: false)
      Label_5:
       LINE 11 -> Label_5
       FRAME[type: F_SAME, locals: 0, local: {com.SwitchTestClass, integer, integer, com.github.jonathanxd.codeapi.test.SwitchTest_$TestEnum, java.lang.String, java.lang.Object}, stacks: 0, stack: {}]
        getstatic java.lang.System.out (type: java.io.PrintStream)
        ldc "5"
        invokevirtual java.io.PrintStream.println(java.lang.Object)void (ownerIsInterface: false)
      Label_8:
       LINE 12 -> Label_8
        goto Label_7
      Label_3:
       LINE 13 -> Label_3
       FRAME[type: F_SAME, locals: 0, local: {com.SwitchTestClass, integer, integer, com.github.jonathanxd.codeapi.test.SwitchTest_$TestEnum, java.lang.String, java.lang.Object}, stacks: 0, stack: {}]
        getstatic java.lang.System.out (type: java.io.PrintStream)
        ldc "default"
        invokevirtual java.io.PrintStream.println(java.lang.Object)void (ownerIsInterface: false)
      Label_7:
       LINE 4 -> Label_7
       FRAME[type: F_SAME, locals: 0, local: {com.SwitchTestClass, integer, integer, com.github.jonathanxd.codeapi.test.SwitchTest_$TestEnum, java.lang.String, java.lang.Object}, stacks: 0, stack: {}]
        iload 2
        lookupSwitch {
            handler 1: Label_9
            handler 10: Label_10
            handler 100: Label_11
            default: Label_12
        }
      Label_9:
       LINE 14 -> Label_9
       FRAME[type: F_SAME, locals: 0, local: {com.SwitchTestClass, integer, integer, com.github.jonathanxd.codeapi.test.SwitchTest_$TestEnum, java.lang.String, java.lang.Object}, stacks: 0, stack: {}]
        getstatic java.lang.System.out (type: java.io.PrintStream)
        ldc "1"
        invokevirtual java.io.PrintStream.println(java.lang.Object)void (ownerIsInterface: false)
      Label_13:
       LINE 15 -> Label_13
        goto Label_14
      Label_10:
       LINE 16 -> Label_10
       FRAME[type: F_SAME, locals: 0, local: {com.SwitchTestClass, integer, integer, com.github.jonathanxd.codeapi.test.SwitchTest_$TestEnum, java.lang.String, java.lang.Object}, stacks: 0, stack: {}]
        getstatic java.lang.System.out (type: java.io.PrintStream)
        ldc "10"
        invokevirtual java.io.PrintStream.println(java.lang.Object)void (ownerIsInterface: false)
      Label_15:
       LINE 17 -> Label_15
        goto Label_14
      Label_11:
       LINE 18 -> Label_11
       FRAME[type: F_SAME, locals: 0, local: {com.SwitchTestClass, integer, integer, com.github.jonathanxd.codeapi.test.SwitchTest_$TestEnum, java.lang.String, java.lang.Object}, stacks: 0, stack: {}]
        getstatic java.lang.System.out (type: java.io.PrintStream)
        ldc "100"
        invokevirtual java.io.PrintStream.println(java.lang.Object)void (ownerIsInterface: false)
      Label_16:
       LINE 19 -> Label_16
        goto Label_14
      Label_12:
       LINE 20 -> Label_12
       FRAME[type: F_SAME, locals: 0, local: {com.SwitchTestClass, integer, integer, com.github.jonathanxd.codeapi.test.SwitchTest_$TestEnum, java.lang.String, java.lang.Object}, stacks: 0, stack: {}]
        getstatic java.lang.System.out (type: java.io.PrintStream)
        ldc "default"
        invokevirtual java.io.PrintStream.println(java.lang.Object)void (ownerIsInterface: false)
      Label_14:
       LINE 5 -> Label_14
       FRAME[type: F_SAME, locals: 0, local: {com.SwitchTestClass, integer, integer, com.github.jonathanxd.codeapi.test.SwitchTest_$TestEnum, java.lang.String, java.lang.Object}, stacks: 0, stack: {}]
        getstatic com.SwitchTestClass$com_github_jonathanxd_codeapi_test_SwitchTest__TestEnum$SwitchOnEnum$Mappings.ENUM_MAP (type: int[])
        aload 3
        invokevirtual java.lang.Enum.ordinal()int (ownerIsInterface: false)
        iaload
        tableSwitch(1..2) {
            handler 0: Label_17
            handler 1: Label_18
            default: Label_19
        }
      Label_17:
       LINE 21 -> Label_17
       FRAME[type: F_SAME, locals: 0, local: {com.SwitchTestClass, integer, integer, com.github.jonathanxd.codeapi.test.SwitchTest_$TestEnum, java.lang.String, java.lang.Object}, stacks: 0, stack: {}]
        getstatic java.lang.System.out (type: java.io.PrintStream)
        ldc "A"
        invokevirtual java.io.PrintStream.println(java.lang.Object)void (ownerIsInterface: false)
      Label_20:
       LINE 22 -> Label_20
        goto Label_21
      Label_18:
       LINE 23 -> Label_18
       FRAME[type: F_SAME, locals: 0, local: {com.SwitchTestClass, integer, integer, com.github.jonathanxd.codeapi.test.SwitchTest_$TestEnum, java.lang.String, java.lang.Object}, stacks: 0, stack: {}]
        getstatic java.lang.System.out (type: java.io.PrintStream)
        ldc "B"
        invokevirtual java.io.PrintStream.println(java.lang.Object)void (ownerIsInterface: false)
      Label_19:
       LINE 24 -> Label_19
       FRAME[type: F_SAME, locals: 0, local: {com.SwitchTestClass, integer, integer, com.github.jonathanxd.codeapi.test.SwitchTest_$TestEnum, java.lang.String, java.lang.Object}, stacks: 0, stack: {}]
        getstatic java.lang.System.out (type: java.io.PrintStream)
        ldc "B or default"
        invokevirtual java.io.PrintStream.println(java.lang.Object)void (ownerIsInterface: false)
      Label_21:
       LINE 6 -> Label_21
       FRAME[type: F_SAME, locals: 0, local: {com.SwitchTestClass, integer, integer, com.github.jonathanxd.codeapi.test.SwitchTest_$TestEnum, java.lang.String, java.lang.Object}, stacks: 0, stack: {}]
        aload 4
        invokevirtual java.lang.Object.hashCode()int (ownerIsInterface: false)
        lookupSwitch {
            handler 2087: Label_22
            handler 2805: Label_23
            handler 62242209: Label_24
            default: Label_25
        }
      Label_22:
       LINE 25 -> Label_22
       FRAME[type: F_SAME, locals: 0, local: {com.SwitchTestClass, integer, integer, com.github.jonathanxd.codeapi.test.SwitchTest_$TestEnum, java.lang.String, java.lang.Object}, stacks: 0, stack: {}]
        aload 4
        ldc "AH"
        invokevirtual java.lang.Object.equals(java.lang.Object)boolean (ownerIsInterface: false)
        ifeq Label_25
      Label_26:
       LINE 26 -> Label_26
        getstatic java.lang.System.out (type: java.io.PrintStream)
        ldc "AH"
        invokevirtual java.io.PrintStream.println(java.lang.Object)void (ownerIsInterface: false)
      Label_27:
       LINE 27 -> Label_27
        goto Label_28
      Label_23:
       LINE 28 -> Label_23
       FRAME[type: F_SAME, locals: 0, local: {com.SwitchTestClass, integer, integer, com.github.jonathanxd.codeapi.test.SwitchTest_$TestEnum, java.lang.String, java.lang.Object}, stacks: 0, stack: {}]
        aload 4
        ldc "XM"
        invokevirtual java.lang.Object.equals(java.lang.Object)boolean (ownerIsInterface: false)
        ifeq Label_25
      Label_29:
       LINE 29 -> Label_29
        getstatic java.lang.System.out (type: java.io.PrintStream)
        ldc "XM"
        invokevirtual java.io.PrintStream.println(java.lang.Object)void (ownerIsInterface: false)
      Label_30:
       LINE 30 -> Label_30
        goto Label_28
      Label_24:
       LINE 31 -> Label_24
       FRAME[type: F_SAME, locals: 0, local: {com.SwitchTestClass, integer, integer, com.github.jonathanxd.codeapi.test.SwitchTest_$TestEnum, java.lang.String, java.lang.Object}, stacks: 0, stack: {}]
        aload 4
        ldc "AHEAD"
        invokevirtual java.lang.Object.equals(java.lang.Object)boolean (ownerIsInterface: false)
        ifeq Label_25
      Label_31:
       LINE 32 -> Label_31
        getstatic java.lang.System.out (type: java.io.PrintStream)
        ldc "AHEAD"
        invokevirtual java.io.PrintStream.println(java.lang.Object)void (ownerIsInterface: false)
      Label_32:
       LINE 33 -> Label_32
        goto Label_28
      Label_25:
       LINE 34 -> Label_25
       FRAME[type: F_SAME, locals: 0, local: {com.SwitchTestClass, integer, integer, com.github.jonathanxd.codeapi.test.SwitchTest_$TestEnum, java.lang.String, java.lang.Object}, stacks: 0, stack: {}]
        getstatic java.lang.System.out (type: java.io.PrintStream)
        ldc "default"
        invokevirtual java.io.PrintStream.println(java.lang.Object)void (ownerIsInterface: false)
      Label_28:
       LINE 7 -> Label_28
       FRAME[type: F_SAME, locals: 0, local: {com.SwitchTestClass, integer, integer, com.github.jonathanxd.codeapi.test.SwitchTest_$TestEnum, java.lang.String, java.lang.Object}, stacks: 0, stack: {}]
        aload 5
        invokevirtual java.lang.Object.hashCode()int (ownerIsInterface: false)
        lookupSwitch {
            handler 0: Label_33
            default: Label_34
        }
      Label_33:
       LINE 35 -> Label_33
       FRAME[type: F_SAME, locals: 0, local: {com.SwitchTestClass, integer, integer, com.github.jonathanxd.codeapi.test.SwitchTest_$TestEnum, java.lang.String, java.lang.Object}, stacks: 0, stack: {}]
        getstatic java.lang.System.out (type: java.io.PrintStream)
        ldc "Zero"
        invokevirtual java.io.PrintStream.println(java.lang.Object)void (ownerIsInterface: false)
      Label_35:
       LINE 36 -> Label_35
        goto Label_36
      Label_34:
       LINE 37 -> Label_34
       FRAME[type: F_SAME, locals: 0, local: {com.SwitchTestClass, integer, integer, com.github.jonathanxd.codeapi.test.SwitchTest_$TestEnum, java.lang.String, java.lang.Object}, stacks: 0, stack: {}]
        getstatic java.lang.System.out (type: java.io.PrintStream)
        ldc "default"
        invokevirtual java.io.PrintStream.println(java.lang.Object)void (ownerIsInterface: false)
      Label_36:
       FRAME[type: F_SAME, locals: 0, local: {com.SwitchTestClass, integer, integer, com.github.jonathanxd.codeapi.test.SwitchTest_$TestEnum, java.lang.String, java.lang.Object}, stacks: 0, stack: {}]
        return
      Label_37:
      LOCAL_VARIABLE[index: 0, name: this, desc: Lcom/SwitchTestClass;, signature: null, start: Label_0, end: Label_37]
      LOCAL_VARIABLE[index: 1, name: number, desc: I, signature: null, start: Label_0, end: Label_37]
      LOCAL_VARIABLE[index: 2, name: number2, desc: I, signature: null, start: Label_0, end: Label_37]
      LOCAL_VARIABLE[index: 3, name: testEnum, desc: Lcom/github/jonathanxd/codeapi/test/SwitchTest_$TestEnum;, signature: null, start: Label_0, end: Label_37]
      LOCAL_VARIABLE[index: 4, name: str, desc: Ljava/lang/String;, signature: null, start: Label_0, end: Label_37]
      LOCAL_VARIABLE[index: 5, name: o, desc: Ljava/lang/Object;, signature: null, start: Label_0, end: Label_37]
      MAX_STACK: 2, MAX_LOCALS: 6
    }

    !access: 8 (PACKAGE_PRIVATE, ACC_STATIC)
    static void <clinit>() {
        return
      MAX_STACK: 0, MAX_LOCALS: 0
    }
}