md5: a469f4a5548caa7ffcbff0cff732e755

version: Java 8 (52)
access: ACC_PUBLIC (33)

source: InvocationsTest__Generated.cai

public class fullName.InvocationsTest__Generated extends java.lang.Object {

    !access: ACC_PUBLIC, ACC_FINAL (17)
    public final java.lang.String FIELD
    !access: ACC_PUBLIC, ACC_FINAL (17)
    public final int n

    !access: ACC_PUBLIC (1)
    public void <init>() {
      desc: ()V 
      maxStack: 2, maxLocals: 1 
      Label_0:
        aload 0
        invokespecial java.lang.Object.<init>()void (ownerIsInterface: false)
        aload 0
        ldc "AVD"              // type: java.lang.String
        putfield fullName.InvocationsTest__Generated.FIELD (type: java.lang.String)
        aload 0
        bipush 15
        putfield fullName.InvocationsTest__Generated.n (type: int)
      Label_1:
       LINE 1 -> Label_1
        getstatic java.lang.System.out (type: java.io.PrintStream)
        ldc "Hello"              // type: java.lang.String
        invokevirtual java.io.PrintStream.println(java.lang.Object)void (ownerIsInterface: false)
      Label_2:
       LINE 2 -> Label_2
        aload 0
        ldc "Oi"              // type: java.lang.String
        invokevirtual fullName.InvocationsTest__Generated.printIt(java.lang.Object)void (ownerIsInterface: false)
        return
      Label_3:
      LocalVariables {
        index: 0, name: this, start: Label_0, end: Label_3, type: fullName.InvocationsTest__Generated, signature: null
      }
    }
    
    !access: ACC_PUBLIC (1)
    !parameter[name: n, access:  (0)]
    public void printIt(java.lang.Object) {
      desc: (Ljava/lang/Object;)V 
      maxStack: 2, maxLocals: 3 
      Label_0:
       LINE 3 -> Label_0
        aload 1
        ifnull Label_2
      Label_1:
       LINE 7 -> Label_1
        getstatic java.lang.System.out (type: java.io.PrintStream)
        ldc "Hello :D"              // type: java.lang.String
        invokevirtual java.io.PrintStream.println(java.lang.Object)void (ownerIsInterface: false)
      Label_2:
       LINE 4 -> Label_2
       FRAME[type: F_SAME, locals: 0, local: {}, stacks: 0, stack: {}]
        ldc "DingDong"              // type: java.lang.String
      Label_3:
        astore 2
      Label_4:
       LINE 5 -> Label_4
        getstatic java.lang.System.out (type: java.io.PrintStream)
        aload 2
        invokevirtual java.io.PrintStream.println(java.lang.Object)void (ownerIsInterface: false)
      Label_5:
       LINE 6 -> Label_5
        getstatic java.lang.System.out (type: java.io.PrintStream)
        aload 1
        invokevirtual java.io.PrintStream.println(java.lang.Object)void (ownerIsInterface: false)
        return
      Label_6:
      LocalVariables {
        index: 2, name: dingdong, start: Label_3, end: Label_6, type: java.lang.String, signature: null
        index: 1, name: n, start: Label_0, end: Label_6, type: java.lang.Object, signature: null
        index: 0, name: this, start: Label_0, end: Label_6, type: fullName.InvocationsTest__Generated, signature: null
      }
    }
    
    !access: ACC_PUBLIC (1)
    !parameter[name: x, access:  (0)]
    public boolean check(int) {
      desc: (I)Z 
      maxStack: 4, maxLocals: 7 
      Label_0:
       LINE 8 -> Label_0
        ldc "xy"              // type: java.lang.String
        ldc "yz"              // type: java.lang.String
        invokestatic com.github.jonathanxd.codeapi.test.InvocationsTest_.bmp(java.lang.String, java.lang.String)void (ownerIsInterface: false)
      Label_1:
       LINE 9 -> Label_1
        getstatic java.lang.System.out (type: java.io.PrintStream)
        ldc "Invoke Interface ->"              // type: java.lang.String
        invokevirtual java.io.PrintStream.println(java.lang.Object)void (ownerIsInterface: false)
      Label_2:
       LINE 10 -> Label_2
        new com.github.jonathanxd.codeapi.test.WorldGreeter
        dup
        invokespecial com.github.jonathanxd.codeapi.test.WorldGreeter.<init>()void (ownerIsInterface: false)
      Label_3:
        astore 2
      Label_4:
       LINE 11 -> Label_4
        aload 2
        invokeinterface com.github.jonathanxd.codeapi.test.Greeter.hello()java.lang.String (ownerIsInterface: true)
      Label_5:
        astore 3
      Label_6:
       LINE 12 -> Label_6
        getstatic java.lang.System.out (type: java.io.PrintStream)
        aload 3
        invokevirtual java.io.PrintStream.println(java.lang.Object)void (ownerIsInterface: false)
      Label_7:
       LINE 13 -> Label_7
        getstatic java.lang.System.out (type: java.io.PrintStream)
        ldc "Invoke Interface <-"              // type: java.lang.String
        invokevirtual java.io.PrintStream.println(java.lang.Object)void (ownerIsInterface: false)
      Label_8:
       LINE 14 -> Label_8
        getstatic java.lang.System.out (type: java.io.PrintStream)
        ldc "Invoke Dynamic ->"              // type: java.lang.String
        invokevirtual java.io.PrintStream.println(java.lang.Object)void (ownerIsInterface: false)
      Label_9:
       LINE 15 -> Label_9
        invokedynamic get()java.util.function.Supplier [
          // Bootstrap method
          java.lang.invoke.LambdaMetafactory.metafactory(java.lang.invoke.MethodHandles$Lookup, java.lang.String, java.lang.invoke.MethodType, java.lang.invoke.MethodType, java.lang.invoke.MethodHandle, java.lang.invoke.MethodType)java.lang.invoke.CallSite (tag: h_invokestatic, itf: false) [
            // Arguments
            ()Ljava/lang/Object;
            fullName.InvocationsTest__Generated.$$lambda$0()java.lang.String (tag: h_invokestatic, itf: false)
            ()Ljava/lang/Object;
          ]
        ]
      Label_10:
        astore 4
      Label_11:
       LINE 16 -> Label_11
        getstatic java.lang.System.out (type: java.io.PrintStream)
        aload 4
        invokeinterface java.util.function.Supplier.get()java.lang.Object (ownerIsInterface: true)
        checkcast java.lang.String
        invokevirtual java.io.PrintStream.println(java.lang.Object)void (ownerIsInterface: false)
      Label_12:
       LINE 17 -> Label_12
        aload 2
        invokedynamic get(com.github.jonathanxd.codeapi.test.Greeter)java.util.function.Supplier [
          // Bootstrap method
          java.lang.invoke.LambdaMetafactory.metafactory(java.lang.invoke.MethodHandles$Lookup, java.lang.String, java.lang.invoke.MethodType, java.lang.invoke.MethodType, java.lang.invoke.MethodHandle, java.lang.invoke.MethodType)java.lang.invoke.CallSite (tag: h_invokestatic, itf: false) [
            // Arguments
            ()Ljava/lang/Object;
            com.github.jonathanxd.codeapi.test.Greeter.hello()java.lang.String (tag: h_invokeinterface, itf: true)
            ()Ljava/lang/String;
          ]
        ]
      Label_13:
        astore 5
      Label_14:
       LINE 18 -> Label_14
        aload 5
        invokeinterface java.util.function.Supplier.get()java.lang.Object (ownerIsInterface: true)
        checkcast java.lang.String
      Label_15:
        astore 6
      Label_16:
       LINE 19 -> Label_16
        getstatic java.lang.System.out (type: java.io.PrintStream)
        aload 6
        invokevirtual java.io.PrintStream.println(java.lang.Object)void (ownerIsInterface: false)
      Label_17:
       LINE 20 -> Label_17
        getstatic java.lang.System.out (type: java.io.PrintStream)
        ldc "Invoke Dynamic <-"              // type: java.lang.String
        invokevirtual java.io.PrintStream.println(java.lang.Object)void (ownerIsInterface: false)
      Label_18:
       LINE 21 -> Label_18
        getstatic java.lang.System.out (type: java.io.PrintStream)
        ldc "Invoke Dynamic Bootstrap ->"              // type: java.lang.String
        invokevirtual java.io.PrintStream.println(java.lang.Object)void (ownerIsInterface: false)
      Label_19:
       LINE 22 -> Label_19
        ldc "World"              // type: java.lang.String
        invokedynamic helloWorld(java.lang.String)void [
          // Bootstrap method
          com.github.jonathanxd.codeapi.test.InvocationsTest_.myBootstrap(java.lang.invoke.MethodHandles$Lookup, java.lang.String, java.lang.invoke.MethodType, java.lang.Object[])java.lang.invoke.CallSite (tag: h_invokestatic, itf: false) [
          ]
        ]
      Label_20:
       LINE 23 -> Label_20
        getstatic java.lang.System.out (type: java.io.PrintStream)
        ldc "Invoke Dynamic Bootstrap <-"              // type: java.lang.String
        invokevirtual java.io.PrintStream.println(java.lang.Object)void (ownerIsInterface: false)
      Label_21:
       LINE 24 -> Label_21
        iload 1
        bipush 9
        if_icmpeq Label_22
        iload 1
        bipush 7
        if_icmpne Label_23
      Label_22:
       LINE 28 -> Label_22
       FRAME[type: F_FULL, locals: 7, local: {Reference[fullName.InvocationsTest__Generated], Primitive[integer], Reference[com.github.jonathanxd.codeapi.test.WorldGreeter], Reference[java.lang.String], Reference[java.util.function.Supplier], Reference[java.util.function.Supplier], Reference[java.lang.String]}, stacks: 0, stack: {}]
        iconst_0
        ireturn
      Label_23:
       LINE 25 -> Label_23
       FRAME[type: F_SAME, locals: 0, local: {}, stacks: 0, stack: {}]
        getstatic java.lang.System.out (type: java.io.PrintStream)
        new java.lang.Integer
        dup
        iload 1
        invokespecial java.lang.Integer.<init>(int)void (ownerIsInterface: false)
        checkcast java.lang.Object
        invokevirtual java.io.PrintStream.println(java.lang.Object)void (ownerIsInterface: false)
      Label_24:
       LINE 26 -> Label_24
        iconst_1
        ireturn
      Label_25:
      LocalVariables {
        index: 6, name: str, start: Label_15, end: Label_25, type: java.lang.String, signature: null
        index: 5, name: supplier, start: Label_13, end: Label_25, type: java.util.function.Supplier, signature: null
        index: 4, name: supplier2, start: Label_10, end: Label_25, type: java.util.function.Supplier, signature: null
        index: 3, name: greetingVar, start: Label_5, end: Label_25, type: java.lang.String, signature: null
        index: 2, name: greeter, start: Label_3, end: Label_25, type: com.github.jonathanxd.codeapi.test.Greeter, signature: null
        index: 1, name: x, start: Label_0, end: Label_25, type: int, signature: null
        index: 0, name: this, start: Label_0, end: Label_25, type: fullName.InvocationsTest__Generated, signature: null
      }
    }
    
    !access: ACC_PRIVATE, ACC_STATIC (10)
    private static java.lang.String $$lambda$0() {
      desc: ()Ljava/lang/String; 
      maxStack: 1, maxLocals: 0 
      Label_0:
       LINE 27 -> Label_0
        ldc "BRB"              // type: java.lang.String
        areturn
    }
    
    !access: PACKAGE_PRIVATE, ACC_STATIC (8)
    static void <clinit>() {
      desc: ()V 
      maxStack: 0, maxLocals: 0 
        return
    }
    
}