md5: ddd6803193a576477d0ee0e0835c7583

version: Java 8 (52)
access: ACC_PUBLIC (33)

source: TestFeatures_.cai

public class fullName.TestFeatures_ extends java.lang.Object {

    !access: ACC_PUBLIC, ACC_FINAL (17)
    public final java.lang.String FIELD
    !access: ACC_PUBLIC, ACC_FINAL (17)
    public final int n

    !access: ACC_PUBLIC (1)
    public void <init>() {
      desc: ()V 
      maxStack: 2, maxLocals: 1 
      Label_0:
        aload 0
        invokespecial java.lang.Object.<init>()void (ownerIsInterface: false)
        aload 0
        ldc "AVD"              // type: java.lang.String
        putfield fullName.TestFeatures_.FIELD (type: java.lang.String)
        aload 0
        bipush 15
        putfield fullName.TestFeatures_.n (type: int)
      Label_1:
       LINE 1 -> Label_1
        getstatic java.lang.System.out (type: java.io.PrintStream)
        ldc "Hello"              // type: java.lang.String
        invokevirtual java.io.PrintStream.println(java.lang.Object)void (ownerIsInterface: false)
      Label_2:
       LINE 2 -> Label_2
        aload 0
        ldc "Oi"              // type: java.lang.String
        invokevirtual fullName.TestFeatures_.printIt(java.lang.Object)void (ownerIsInterface: false)
        return
      Label_3:
      LocalVariables {
        index: 0, name: this, start: Label_0, end: Label_3, type: fullName.TestFeatures_, signature: null
      }
    }
    
    !access: ACC_PUBLIC (1)
    !parameter[name: n, access:  (0)]
    public void printIt(java.lang.Object) {
      desc: (Ljava/lang/Object;)V 
      maxStack: 2, maxLocals: 3 
      Label_0:
       LINE 3 -> Label_0
        aload 1
        ifnull Label_2
      Label_1:
       LINE 7 -> Label_1
        getstatic java.lang.System.out (type: java.io.PrintStream)
        ldc "Hello :D"              // type: java.lang.String
        invokevirtual java.io.PrintStream.println(java.lang.Object)void (ownerIsInterface: false)
      Label_2:
       LINE 4 -> Label_2
       FRAME[type: F_SAME, locals: 0, local: {}, stacks: 0, stack: {}]
        ldc "DingDong"              // type: java.lang.String
      Label_3:
        astore 2
      Label_4:
       LINE 5 -> Label_4
        getstatic java.lang.System.out (type: java.io.PrintStream)
        aload 2
        invokevirtual java.io.PrintStream.println(java.lang.Object)void (ownerIsInterface: false)
      Label_5:
       LINE 6 -> Label_5
        getstatic java.lang.System.out (type: java.io.PrintStream)
        aload 1
        invokevirtual java.io.PrintStream.println(java.lang.Object)void (ownerIsInterface: false)
        return
      Label_6:
      LocalVariables {
        index: 2, name: dingdong, start: Label_3, end: Label_6, type: java.lang.String, signature: null
        index: 1, name: n, start: Label_0, end: Label_6, type: java.lang.Object, signature: null
        index: 0, name: this, start: Label_0, end: Label_6, type: fullName.TestFeatures_, signature: null
      }
    }
    
    !access: ACC_PUBLIC (1)
    !parameter[name: x, access:  (0)]
    public boolean check(int) {
      desc: (I)Z 
      maxStack: 4, maxLocals: 2 
      Label_0:
       LINE 8 -> Label_0
        iload 1
        bipush 9
        if_icmpeq Label_1
        iload 1
        bipush 7
        if_icmpne Label_2
      Label_1:
       LINE 11 -> Label_1
       FRAME[type: F_SAME, locals: 0, local: {}, stacks: 0, stack: {}]
        iconst_0
        ireturn
      Label_2:
       LINE 9 -> Label_2
       FRAME[type: F_SAME, locals: 0, local: {}, stacks: 0, stack: {}]
        getstatic java.lang.System.out (type: java.io.PrintStream)
        new java.lang.Integer
        dup
        iload 1
        invokespecial java.lang.Integer.<init>(int)void (ownerIsInterface: false)
        checkcast java.lang.Object
        invokevirtual java.io.PrintStream.println(java.lang.Object)void (ownerIsInterface: false)
      Label_3:
       LINE 10 -> Label_3
        iconst_1
        ireturn
      Label_4:
      LocalVariables {
        index: 1, name: x, start: Label_0, end: Label_4, type: int, signature: null
        index: 0, name: this, start: Label_0, end: Label_4, type: fullName.TestFeatures_, signature: null
      }
    }
    
    !access: PACKAGE_PRIVATE, ACC_STATIC (8)
    static void <clinit>() {
      desc: ()V 
      maxStack: 0, maxLocals: 0 
        return
    }
    
}