md5: 4177efe12b269020eb3c064d0b1a8bd0

version: 52 (Java 8)
access: 33 (ACC_PUBLIC)

source: TestBytecode_Invocations_Generated.cai, debug: null
public class fullName.TestBytecode_Invocations_Generated extends java.lang.Object {

    !access: 17 (ACC_PUBLIC, ACC_FINAL)
    public final java.lang.String FIELD

    !access: 17 (ACC_PUBLIC, ACC_FINAL)
    public final int n

    !access: 1 (ACC_PUBLIC)
    public void <init>() {
      Label_0:
        aload 0
        invokespecial java.lang.Object.<init>()void (ownerIsInterface: false)
        aload 0
        ldc "AVD"
        putfield fullName.TestBytecode_Invocations_Generated.FIELD (type: java.lang.String)
        aload 0
        bipush 15
        putfield fullName.TestBytecode_Invocations_Generated.n (type: int)
      Label_1:
       LINE 7 -> Label_1
        getstatic java.lang.System.out (type: java.io.PrintStream)
        ldc "Hello"
        invokevirtual java.io.PrintStream.println(java.lang.Object)void (ownerIsInterface: false)
      Label_2:
       LINE 8 -> Label_2
        aload 0
        ldc "Oi"
        invokevirtual fullName.TestBytecode_Invocations_Generated.printIt(java.lang.Object)void (ownerIsInterface: false)
        getstatic java.lang.System.out (type: java.io.PrintStream)
        ldc "Inicializado!"
        invokevirtual java.io.PrintStream.println(java.lang.Object)void (ownerIsInterface: false)
        return
      Label_3:
      LOCAL_VARIABLE[index: 0, name: this, desc: LfullName/TestBytecode_Invocations_Generated;, signature: null, start: Label_0, end: Label_3]
      MAX_STACK: 2, MAX_LOCALS: 1
    }

    !access: 1 (ACC_PUBLIC)
    public void printIt(java.lang.Object) {
      Label_0:
       LINE 9 -> Label_0
        aload 1
        ifnull Label_1
      Label_2:
       LINE 13 -> Label_2
        getstatic java.lang.System.out (type: java.io.PrintStream)
        ldc "Hello :D"
        invokevirtual java.io.PrintStream.println(java.lang.Object)void (ownerIsInterface: false)
      Label_1:
       LINE 10 -> Label_1
       FRAME[type: F_SAME, locals: 0, local: {}, stacks: 0, stack: {}]
        ldc "DingDong"
      Label_3:
        astore 2
      Label_4:
       LINE 11 -> Label_4
        getstatic java.lang.System.out (type: java.io.PrintStream)
        aload 2
        invokevirtual java.io.PrintStream.println(java.lang.Object)void (ownerIsInterface: false)
      Label_5:
       LINE 12 -> Label_5
        getstatic java.lang.System.out (type: java.io.PrintStream)
        aload 1
        invokevirtual java.io.PrintStream.println(java.lang.Object)void (ownerIsInterface: false)
        return
      Label_6:
      LOCAL_VARIABLE[index: 0, name: this, desc: LfullName/TestBytecode_Invocations_Generated;, signature: null, start: Label_0, end: Label_6]
      LOCAL_VARIABLE[index: 1, name: n, desc: Ljava/lang/Object;, signature: null, start: Label_0, end: Label_6]
      LOCAL_VARIABLE[index: 2, name: dingdong, desc: Ljava/lang/String;, signature: null, start: Label_3, end: Label_6]
      MAX_STACK: 2, MAX_LOCALS: 3
    }

    !access: 1 (ACC_PUBLIC)
    public boolean check(int) {
      Label_0:
       LINE 14 -> Label_0
        ldc "xy"
        ldc "yz"
        invokestatic com.github.jonathanxd.codeapi.test.asm.TestBytecode_Invocations.bmp(java.lang.String, java.lang.String)void (ownerIsInterface: false)
      Label_1:
       LINE 15 -> Label_1
        getstatic java.lang.System.out (type: java.io.PrintStream)
        ldc "Invoke Interface ->"
        invokevirtual java.io.PrintStream.println(java.lang.Object)void (ownerIsInterface: false)
      Label_2:
       LINE 16 -> Label_2
        new com.github.jonathanxd.codeapi.test.WorldGreeter
        dup
        invokespecial com.github.jonathanxd.codeapi.test.WorldGreeter.<init>()void (ownerIsInterface: false)
      Label_3:
        astore 2
      Label_4:
       LINE 17 -> Label_4
        aload 2
        invokeinterface com.github.jonathanxd.codeapi.test.Greeter.hello()java.lang.String (ownerIsInterface: true)
      Label_5:
        astore 3
      Label_6:
       LINE 18 -> Label_6
        getstatic java.lang.System.out (type: java.io.PrintStream)
        aload 3
        invokevirtual java.io.PrintStream.println(java.lang.Object)void (ownerIsInterface: false)
      Label_7:
       LINE 19 -> Label_7
        getstatic java.lang.System.out (type: java.io.PrintStream)
        ldc "Invoke Interface <-"
        invokevirtual java.io.PrintStream.println(java.lang.Object)void (ownerIsInterface: false)
      Label_8:
       LINE 20 -> Label_8
        getstatic java.lang.System.out (type: java.io.PrintStream)
        ldc "Invoke Dynamic ->"
        invokevirtual java.io.PrintStream.println(java.lang.Object)void (ownerIsInterface: false)
      Label_9:
       LINE 21 -> Label_9
        invokedynamic get()java.util.function.Supplier (bootstrap: java.lang.invoke.LambdaMetafactory.metafactory(java.lang.invoke.MethodHandles$Lookup, java.lang.String, java.lang.invoke.MethodType, java.lang.invoke.MethodType, java.lang.invoke.MethodHandle, java.lang.invoke.MethodType)java.lang.invoke.CallSite (tag: h_invokestatic, itf: false), args: [()Ljava/lang/Object;, fullName.TestBytecode_Invocations_Generated.fragment$$190175436()java.lang.String (tag: h_invokestatic, itf: false), ()Ljava/lang/String;])
      Label_10:
        astore 4
      Label_11:
       LINE 22 -> Label_11
        getstatic java.lang.System.out (type: java.io.PrintStream)
        aload 4
        invokeinterface java.util.function.Supplier.get()java.lang.Object (ownerIsInterface: true)
        checkcast java.lang.String
        invokevirtual java.io.PrintStream.println(java.lang.Object)void (ownerIsInterface: false)
      Label_12:
       LINE 23 -> Label_12
        aload 2
        invokedynamic get(com.github.jonathanxd.codeapi.test.Greeter)java.util.function.Supplier (bootstrap: java.lang.invoke.LambdaMetafactory.metafactory(java.lang.invoke.MethodHandles$Lookup, java.lang.String, java.lang.invoke.MethodType, java.lang.invoke.MethodType, java.lang.invoke.MethodHandle, java.lang.invoke.MethodType)java.lang.invoke.CallSite (tag: h_invokestatic, itf: false), args: [()Ljava/lang/Object;, com.github.jonathanxd.codeapi.test.Greeter.hello()java.lang.String (tag: h_invokeinterface, itf: true), ()Ljava/lang/String;])
      Label_13:
        astore 5
      Label_14:
       LINE 24 -> Label_14
        aload 5
        invokeinterface java.util.function.Supplier.get()java.lang.Object (ownerIsInterface: true)
        checkcast java.lang.String
      Label_15:
        astore 6
      Label_16:
       LINE 25 -> Label_16
        getstatic java.lang.System.out (type: java.io.PrintStream)
        aload 6
        invokevirtual java.io.PrintStream.println(java.lang.Object)void (ownerIsInterface: false)
      Label_17:
       LINE 26 -> Label_17
        getstatic java.lang.System.out (type: java.io.PrintStream)
        ldc "Invoke Dynamic <-"
        invokevirtual java.io.PrintStream.println(java.lang.Object)void (ownerIsInterface: false)
      Label_18:
       LINE 27 -> Label_18
        getstatic java.lang.System.out (type: java.io.PrintStream)
        ldc "Invoke Dynamic Bootstrap ->"
        invokevirtual java.io.PrintStream.println(java.lang.Object)void (ownerIsInterface: false)
      Label_19:
       LINE 28 -> Label_19
        ldc "World"
        invokedynamic helloWorld(java.lang.String)void (bootstrap: com.github.jonathanxd.codeapi.test.asm.TestBytecode_Invocations.myBootstrap(java.lang.invoke.MethodHandles$Lookup, java.lang.String, java.lang.invoke.MethodType, java.lang.Object[])java.lang.invoke.CallSite (tag: h_invokestatic, itf: false), args: [])
      Label_20:
       LINE 29 -> Label_20
        getstatic java.lang.System.out (type: java.io.PrintStream)
        ldc "Invoke Dynamic Bootstrap <-"
        invokevirtual java.io.PrintStream.println(java.lang.Object)void (ownerIsInterface: false)
      Label_21:
       LINE 30 -> Label_21
        iload 1
        bipush 9
        if_icmpeq Label_22
        iload 1
        bipush 7
        if_icmpne Label_23
      Label_22:
       LINE 33 -> Label_22
       FRAME[type: F_FULL, locals: 7, local: {fullName.TestBytecode_Invocations_Generated, integer, com.github.jonathanxd.codeapi.test.WorldGreeter, java.lang.String, java.util.function.Supplier, java.util.function.Supplier, java.lang.String}, stacks: 0, stack: {}]
        iconst_0
        ireturn
      Label_23:
       LINE 31 -> Label_23
       FRAME[type: F_SAME, locals: 0, local: {fullName.TestBytecode_Invocations_Generated, integer, com.github.jonathanxd.codeapi.test.WorldGreeter, java.lang.String, java.util.function.Supplier, java.util.function.Supplier, java.lang.String}, stacks: 0, stack: {}]
        getstatic java.lang.System.out (type: java.io.PrintStream)
        new java.lang.Integer
        dup
        iload 1
        invokespecial java.lang.Integer.<init>(int)void (ownerIsInterface: false)
        checkcast java.lang.Object
        invokevirtual java.io.PrintStream.println(java.lang.Object)void (ownerIsInterface: false)
      Label_24:
       LINE 32 -> Label_24
        iconst_1
        ireturn
      Label_25:
      LOCAL_VARIABLE[index: 0, name: this, desc: LfullName/TestBytecode_Invocations_Generated;, signature: null, start: Label_0, end: Label_25]
      LOCAL_VARIABLE[index: 1, name: x, desc: I, signature: null, start: Label_0, end: Label_25]
      LOCAL_VARIABLE[index: 2, name: greeter, desc: Lcom/github/jonathanxd/codeapi/test/Greeter;, signature: null, start: Label_3, end: Label_25]
      LOCAL_VARIABLE[index: 3, name: greetingVar, desc: Ljava/lang/String;, signature: null, start: Label_5, end: Label_25]
      LOCAL_VARIABLE[index: 4, name: supplier2, desc: Ljava/util/function/Supplier;, signature: null, start: Label_10, end: Label_25]
      LOCAL_VARIABLE[index: 5, name: supplier, desc: Ljava/util/function/Supplier;, signature: null, start: Label_13, end: Label_25]
      LOCAL_VARIABLE[index: 6, name: str, desc: Ljava/lang/String;, signature: null, start: Label_15, end: Label_25]
      MAX_STACK: 4, MAX_LOCALS: 7
    }

    !access: 10 (ACC_PRIVATE, ACC_STATIC)
    private static java.lang.String fragment$$190175436() {
      Label_0:
       LINE 34 -> Label_0
        ldc "BRB"
        pop
        ldc "XSD"
        areturn
      Label_1:
       FRAME[type: F_SAME1, locals: 0, local: {}, stacks: 1, stack: {java.lang.Throwable}]
        athrow
      MAX_STACK: 1, MAX_LOCALS: 0
    }

    !access: 8 (PACKAGE_PRIVATE, ACC_STATIC)
    static void <clinit>() {
        return
      MAX_STACK: 0, MAX_LOCALS: 0
    }
}