md5: 4260513e22adda993524052254cdb457

version: Java 8 (52)
access: ACC_PUBLIC (33)

source: MyClass.cai

public class com.MyClass extends java.lang.Object {

    !access: ACC_PUBLIC (1)
    !parameter[name: a, access:  (0)]
    public void test(boolean) {
      desc: (Z)V 
      maxStack: 2, maxLocals: 4 
      Label_0:
       LINE 1 -> Label_0
        iload 1
        ifeq Label_3
      Label_1:
       LINE 2 -> Label_1
       LINE 6 -> Label_1
        getstatic java.lang.System.out (type: java.io.PrintStream)
        ldc "Finally"              // type: java.lang.String
        invokevirtual java.io.PrintStream.println(java.lang.String)void (ownerIsInterface: false)
      Label_2:
       LINE 2 -> Label_2
        return
      Label_3:
       LINE 3 -> Label_3
       FRAME[type: F_SAME, locals: 0, local: {}, stacks: 0, stack: {}]
        getstatic java.lang.System.out (type: java.io.PrintStream)
        ldc "X"              // type: java.lang.String
        invokevirtual java.io.PrintStream.println(java.lang.String)void (ownerIsInterface: false)
      Label_4:
       LINE 4 -> Label_4
        ldc "f"              // type: java.lang.String
        invokestatic java.lang.Class.forName(java.lang.String)java.lang.Class (ownerIsInterface: false)
        pop
      Label_5:
       LINE 6 -> Label_5
        getstatic java.lang.System.out (type: java.io.PrintStream)
        ldc "Finally"              // type: java.lang.String
        invokevirtual java.io.PrintStream.println(java.lang.String)void (ownerIsInterface: false)
      Label_6:
        return
      Label_7:
       FRAME[type: F_SAME1, locals: 0, local: {}, stacks: 1, stack: {Reference[java.lang.ClassNotFoundException]}]
        astore 2
      Label_8:
       LINE 5 -> Label_8
        aload 2
        athrow
      Label_9:
       FRAME[type: F_SAME1, locals: 0, local: {}, stacks: 1, stack: {Reference[java.lang.Throwable]}]
        astore 3
      Label_10:
       LINE 6 -> Label_10
        getstatic java.lang.System.out (type: java.io.PrintStream)
        ldc "Finally"              // type: java.lang.String
        invokevirtual java.io.PrintStream.println(java.lang.String)void (ownerIsInterface: false)
        aload 3
        athrow
      Label_11:
       FRAME[type: F_FULL, locals: 0, local: {}, stacks: 1, stack: {Reference[java.lang.Throwable]}]
        athrow
      Label_12:
      TryCatchBlocks {
        start: Label_0, end: Label_3, handler: Label_7, exception: java.lang.ClassNotFoundException
        start: Label_3, end: Label_6, handler: Label_7, exception: java.lang.ClassNotFoundException
        start: Label_0, end: Label_1, handler: Label_9, exception: null
        start: Label_2, end: Label_3, handler: Label_9, exception: null
        start: Label_3, end: Label_5, handler: Label_9, exception: null
        start: Label_7, end: Label_9, handler: Label_9, exception: null
      }
      LocalVariables {
        index: 2, name: ex, start: Label_7, end: Label_9, type: java.lang.ClassNotFoundException, signature: null
        index: 1, name: a, start: Label_0, end: Label_12, type: boolean, signature: null
        index: 0, name: this, start: Label_0, end: Label_12, type: com.MyClass, signature: null
      }
    }
    
    !access: ACC_PUBLIC (1)
    public void <init>() {
      desc: ()V 
      maxStack: 1, maxLocals: 1 
      Label_0:
        aload 0
        invokespecial java.lang.Object.<init>()void (ownerIsInterface: false)
        return
      Label_1:
      LocalVariables {
        index: 0, name: this, start: Label_0, end: Label_1, type: com.MyClass, signature: null
      }
    }
    
    !access: PACKAGE_PRIVATE, ACC_STATIC (8)
    static void <clinit>() {
      desc: ()V 
      maxStack: 0, maxLocals: 0 
        return
    }
    
}